LICENSE.md
MANIFEST.in
README.md
setup.cfg
setup.py
i18n/__init__.py
jupyter-config/nbconfig/notebook.d/rise.json
rise/__init__.py
rise/_version.py
rise/static/README.md
rise/static/main.js
rise/static/rise.png
rise/static/rise.yaml
risei18n0.egg-info/PKG-INFO
risei18n0.egg-info/SOURCES.txt
risei18n0.egg-info/dependency_links.txt
risei18n0.egg-info/not-zip-safe
risei18n0.egg-info/requires.txt
risei18n0.egg-info/top_level.txt