Metadata-Version: 1.2
Name: risei18n0
Version: 5.3.0
Summary: Reveal.js - Jupyter/IPython Slideshow Extension
Home-page: UNKNOWN
Author: Damián Avila
Author-email: info@oquanta.info
License: BSD-3-Clause
Project-URL: source, http://github.com/damianavila/RISE
Project-URL: documentation, http://rise.readthedocs.io
Project-URL: gitter, https://gitter.im/damianavila/RISE
Keywords: jupyter,ipython,presentation,slides,revealjs
Platform: Linux
Platform: Mac OS X
Platform: Windows
Classifier: Intended Audience :: Developers
Classifier: Intended Audience :: System Administrators
Classifier: Intended Audience :: Science/Research
Classifier: License :: OSI Approved :: BSD License
Classifier: Programming Language :: Python
Classifier: Programming Language :: Python :: 2
Classifier: Programming Language :: Python :: 2.7
Classifier: Programming Language :: Python :: 3
Classifier: Programming Language :: Python :: 3.4
Classifier: Programming Language :: Python :: 3.5
Classifier: Programming Language :: Python :: 3.6
Requires-Python: >=2.7,>=3.4
